hamcode/__init__.py
hamcode/decoder.py
hamcode/encoder.py
hamcode-0.1.0.dist-info/LICENSE
hamcode-0.1.0.dist-info/WHEEL
hamcode-0.1.0.dist-info/METADATA
hamcode-0.1.0.dist-info/RECORD
